stadt_bonn_oparl_api_client/__init__.py
stadt_bonn_oparl_api_client/api/__init__.py
stadt_bonn_oparl_api_client/api/oparl/__init__.py
stadt_bonn_oparl_api_client/api/oparl/agenda_items_agendaitems_get.py
stadt_bonn_oparl_api_client/api/oparl/bodies_bodies_get.py
stadt_bonn_oparl_api_client/api/oparl/consultations_consultations_get.py
stadt_bonn_oparl_api_client/api/oparl/files_files_get.py
stadt_bonn_oparl_api_client/api/oparl/get_meetings_reference_status_meetings_meeting_id_references_get.py
stadt_bonn_oparl_api_client/api/oparl/locations_locations_get.py
stadt_bonn_oparl_api_client/api/oparl/meetings_meetings_get.py
stadt_bonn_oparl_api_client/api/oparl/memberships_memberships_get.py
stadt_bonn_oparl_api_client/api/oparl/organizations_organizations_get.py
stadt_bonn_oparl_api_client/api/oparl/papers_papers_get.py
stadt_bonn_oparl_api_client/api/oparl/persons_persons_get.py
stadt_bonn_oparl_api_client/api/oparl/search_search_get.py
stadt_bonn_oparl_api_client/api/oparl/system_system_get.py
stadt_bonn_oparl_api_client/api/service/__init__.py
stadt_bonn_oparl_api_client/api/service/status_status_get.py
stadt_bonn_oparl_api_client/api/service/version_version_get.py
stadt_bonn_oparl_api_client/client.py
stadt_bonn_oparl_api_client/errors.py
stadt_bonn_oparl_api_client/models/__init__.py
stadt_bonn_oparl_api_client/models/agenda_item_response.py
stadt_bonn_oparl_api_client/models/agenda_item_response_auxiliary_file_type_0_item.py
stadt_bonn_oparl_api_client/models/agenda_item_response_resolution_file_type_0.py
stadt_bonn_oparl_api_client/models/consultation.py
stadt_bonn_oparl_api_client/models/file_list_response.py
stadt_bonn_oparl_api_client/models/file_list_response_links_type_0.py
stadt_bonn_oparl_api_client/models/file_list_response_pagination_type_0.py
stadt_bonn_oparl_api_client/models/file_response.py
stadt_bonn_oparl_api_client/models/http_validation_error.py
stadt_bonn_oparl_api_client/models/location_response.py
stadt_bonn_oparl_api_client-1.8.6.dist-info/METADATA
stadt_bonn_oparl_api_client-1.8.6.dist-info/WHEEL
stadt_bonn_oparl_api_client-1.8.6.dist-info/RECORD
